ssm_bridge/__init__.py
ssm_bridge/model.py
ssm_bridge-0.0.2.dist-info/LICENSE
ssm_bridge-0.0.2.dist-info/METADATA
ssm_bridge-0.0.2.dist-info/WHEEL
ssm_bridge-0.0.2.dist-info/RECORD
