Metadata-Version: 2.3
Name: ssm-bridge
Version: 0.0.2
Summary: SSM-As-VLM-Bridge: State Space Models as Vision-Language Bridge Layers
License: MIT
Keywords: artificial intelligence,deep learning,vision-language,state-space-models,computer-vision,natural-language-processing
Author: Kye Gomez
Author-email: kye@apac.ai
Requires-Python: >=3.10,<4.0
Classifier: Development Status :: 3 - Alpha
Classifier: Intended Audience :: Developers
Classifier: Intended Audience :: Science/Research
Classifier: License :: OSI Approved :: MIT License
Classifier: Programming Language :: Python :: 3
Classifier: Programming Language :: Python :: 3.10
Classifier: Programming Language :: Python :: 3.11
Classifier: Programming Language :: Python :: 3.12
Classifier: Programming Language :: Python :: 3.13
Classifier: Topic :: Scientific/Engineering :: Artificial Intelligence
Classifier: Topic :: Scientific/Engineering :: Image Processing
Classifier: Topic :: Scientific/Engineering :: Information Analysis
Requires-Dist: torch
Project-URL: Documentation, https://github.com/kyegomez/SSM-As-VLM-Bridge
Project-URL: Homepage, https://github.com/kyegomez/SSM-As-VLM-Bridge
Project-URL: Repository, https://github.com/kyegomez/SSM-As-VLM-Bridge
